{"encounters":[{"encountermethod":"Grass","routes":[{"route":"Route 1","encounter_info":{"always":[{"pokemon":"Bidoof","encounterrate":0.1},{"pokemon":"Sentret","encounterrate":0.2},{"pokemon":"Starly","encounterrate":0.1},{"pokemon":"Panpour","encounterrate":0.02}],"day":[{"pokemon":"Zigzagoon","encounterrate":0.08},{"pokemon":"Pidgey","encounterrate":0.2},{"pokemon":"Budew","encounterrate":0.1},{"pokemon":"Rattata","encounterrate":0.2},{"pokemon":"Lillipup","encounterrate":0.1}],"night":[{"pokemon":"Poochyena","encounterrate":0.1},{"pokemon":"Rattata-alola","encounterrate":0.1},{"pokemon":"Hoothoot","encounterrate":0.2},{"pokemon":"Zigzagoon-galar","encounterrate":0.08},{"pokemon":"Seedot","encounterrate":0.1}]}},{"route":"Viridian City","encounter_info":{"always":[{"pokemon":"Mienfoo","encounterrate":0.1},{"pokemon":"Meditite","encounterrate":0.02},{"pokemon":"Starly","encounterrate":0.2}],"day":[{"pokemon":"Morelull","encounterrate":0.1},{"pokemon":"Snover","encounterrate":0.08},{"pokemon":"Machop","encounterrate":0.1},{"pokemon":"Sentret","encounterrate":0.2},{"pokemon":"Sandile","encounterrate":0.1},{"pokemon":"Ponyta","encounterrate":0.1}],"night":[{"pokemon":"Pancham","encounterrate":0.1},{"pokemon":"Ponyta-galar","encounterrate":0.1},{"pokemon":"Marill","encounterrate":0.1},{"pokemon":"Shuppet","encounterrate":0.1},{"pokemon":"Cubchoo","encounterrate":0.08},{"pokemon":"Poochyena","encounterrate":0.2}]}},{"route":"Route 22","encounter_info":{"always":[{"pokemon":"Rockruff","encounterrate":0.04},{"pokemon":"Pansear","encounterrate":0.02},{"pokemon":"Spearow","encounterrate":0.1},{"pokemon":"Mankey","encounterrate":0.2}],"day":[{"pokemon":"Swinub","encounterrate":0.1},{"pokemon":"Wooloo","encounterrate":0.2},{"pokemon":"Snubbull","encounterrate":0.1},{"pokemon":"Budew","encounterrate":0.1},{"pokemon":"Deerling-Summer","encounterrate":0.05},{"pokemon":"Pikipek","encounterrate":0.1}],"night":[{"pokemon":"Sandshrew-alola","encounterrate":0.1},{"pokemon":"Skiddo","encounterrate":0.1},{"pokemon":"Yungoos","encounterrate":0.2},{"pokemon":"Flabebe","encounterrate":0.1},{"pokemon":"Deerling-alolautumn","encounterrate":0.05},{"pokemon":"Rookidee","encounterrate":0.1}]}},{"route":"Route 2","encounter_info":{"always":[{"pokemon":"Shinx","encounterrate":0.2},{"pokemon":"Wingull","encounterrate":0.1},{"pokemon":"Phanpy","encounterrate":0.05},{"pokemon":"Mareep","encounterrate":0.1},{"pokemon":"Skwovet","encounterrate":0.04},{"pokemon":"Pansage","encounterrate":0.02}],"day":[{"pokemon":"Hoppip","encounterrate":0.1},{"pokemon":"Burmy-Sandy","encounterrate":0.04},{"pokemon":"Litleo","encounterrate":0.1},{"pokemon":"Patrat","encounterrate":0.2},{"pokemon":"Sandshrew","encounterrate":0.05}],"night":[{"pokemon":"Houndour","encounterrate":0.1},{"pokemon":"Silicobra","encounterrate":0.05},{"pokemon":"Oddish","encounterrate":0.1},{"pokemon":"Burmy","encounterrate":0.04},{"pokemon":"Poochyena","encounterrate":0.2}]}},{"route":"Viridian Forest","encounter_info":{"always":[{"pokemon":"Grubbin","encounterrate":0.04},{"pokemon":"Pikachu","encounterrate":0.05}],"day":[{"pokemon":"Weedle","encounterrate":0.2},{"pokemon":"Ledyba","encounterrate":0.1},{"pokemon":"Combee","encounterrate":0.1},{"pokemon":"Scatterbug","encounterrate":0.1},{"pokemon":"Nincada","encounterrate":0.1},{"pokemon":"Surskit","encounterrate":0.05},{"pokemon":"Shroomish","encounterrate":0.04},{"pokemon":"Joltik","encounterrate":0.02},{"pokemon":"Caterpie","encounterrate":0.2}],"night":[{"pokemon":"Spinarak ","encounterrate":0.4},{"pokemon":"Blipbug","encounterrate":0.1},{"pokemon":"Burmy-Trash","encounterrate":0.1},{"pokemon":"Sewaddle","encounterrate":0.1},{"pokemon":"Kricketot","encounterrate":0.1},{"pokemon":"Wurmple","encounterrate":0.2},{"pokemon":"Pumpkaboo-XL","encounterrate":0.04},{"pokemon":"Snom","encounterrate":0.02}]}},{"route":"Diglett's Cave 1","encounter_info":{"always":[{"pokemon":"Scraggy","encounterrate":0.1},{"pokemon":"Roggenrola","encounterrate":0.1},{"pokemon":"Noibat","encounterrate":0.1},{"pokemon":"Numel","encounterrate":0.08},{"pokemon":"Nosepass","encounterrate":0.02},{"pokemon":"Trapinch","encounterrate":0.1}],"day":[{"pokemon":"Geodude","encounterrate":0.2},{"pokemon":"Diglett","encounterrate":0.2},{"pokemon":"Sandyghast","encounterrate":0.1}],"night":[{"pokemon":"Geodude-alola","encounterrate":0.2},{"pokemon":"Yamask-galar","encounterrate":0.1},{"pokemon":"Diglett-alola","encounterrate":0.2}]}},{"route":"Pewter City","encounter_info":{"always":[{"pokemon":"Phanpy","encounterrate":0.2},{"pokemon":"Axew","encounterrate":0.02},{"pokemon":"Snover","encounterrate":0.1},{"pokemon":"Yungoos","encounterrate":0.2}],"day":[{"pokemon":"Lotad","encounterrate":0.05},{"pokemon":"Grimer","encounterrate":0.1},{"pokemon":"Meowth","encounterrate":0.05},{"pokemon":"Exeggcute","encounterrate":0.1},{"pokemon":"Numel","encounterrate":0.04},{"pokemon":"Cutiefly","encounterrate":0.04},{"pokemon":"Spoink","encounterrate":0.1}],"night":[{"pokemon":"Sinistea","encounterrate":0.04},{"pokemon":"Meowth-galar","encounterrate":0.05},{"pokemon":"Gastly","encounterrate":0.05},{"pokemon":"Espurr","encounterrate":0.1},{"pokemon":"Grimer-alola","encounterrate":0.1},{"pokemon":"Exeggcute-alola","encounterrate":0.1},{"pokemon":"Applin","encounterrate":0.04}]}},{"route":"Route 3","encounter_info":{"always":[{"pokemon":"Nidoran-F","encounterrate":0.1},{"pokemon":"Flabebe","encounterrate":0.1},{"pokemon":"Stunky","encounterrate":0.2},{"pokemon":"Spearow","encounterrate":0.1},{"pokemon":"Nidoran-M","encounterrate":0.1},{"pokemon":"Glameow","encounterrate":0.04},{"pokemon":"Jigglypuff","encounterrate":0.02}],"day":[{"pokemon":"Ekans","encounterrate":0.2},{"pokemon":"Meowth","encounterrate":0.05},{"pokemon":"Skiddo","encounterrate":0.1}],"night":[{"pokemon":"Nickit","encounterrate":0.2},{"pokemon":"Meowth-alola","encounterrate":0.05},{"pokemon":"Shroomish","encounterrate":0.1}]}},{"route":"Mt. Moon (Main)","encounter_info":{"always":[{"pokemon":"Tyrogue","encounterrate":0.04},{"pokemon":"Zubat","encounterrate":0.2},{"pokemon":"Rockruff","encounterrate":0.1},{"pokemon":"Makuhita","encounterrate":0.1},{"pokemon":"Clefairy","encounterrate":0.04},{"pokemon":"Trapinch","encounterrate":0.02}],"day":[{"pokemon":"Timburr","encounterrate":0.1},{"pokemon":"Geodude","encounterrate":0.2},{"pokemon":"Woobat","encounterrate":0.1},{"pokemon":"Chewtle","encounterrate":0.1}],"night":[{"pokemon":"Geodude-alola","encounterrate":0.2},{"pokemon":"Noibat","encounterrate":0.1},{"pokemon":"Tympole","encounterrate":0.1},{"pokemon":"Machop","encounterrate":0.1}]}},{"route":"Mt. Moon (Tunnels)","encounter_info":{"always":[{"pokemon":"Dunsparce","encounterrate":0.05},{"pokemon":"Teddiursa","encounterrate":0.1},{"pokemon":"Paras","encounterrate":0.8},{"pokemon":"Slugma","encounterrate":0.1}],"day":[{"pokemon":"Cufant","encounterrate":0.02},{"pokemon":"Shuppet","encounterrate":0.08},{"pokemon":"Woobat","encounterrate":0.1},{"pokemon":"Baltoy","encounterrate":0.05}],"night":[{"pokemon":"Misdreavus","encounterrate":0.08},{"pokemon":"Sandile","encounterrate":0.05},{"pokemon":"Mawile","encounterrate":0.02},{"pokemon":"Rockruff","encounterrate":0.1}]}},{"route":"Mt. Moon (Basement)","encounter_info":{"always":[{"pokemon":"Drilbur","encounterrate":0.1},{"pokemon":"Clefairy","encounterrate":0.04},{"pokemon":"Rockruff","encounterrate":0.1},{"pokemon":"Whismur","encounterrate":0.05},{"pokemon":"Smoochum","encounterrate":0.1},{"pokemon":"Onix","encounterrate":0.02},{"pokemon":"Zubat","encounterrate":0.2}],"day":[{"pokemon":"Geodude","encounterrate":0.2},{"pokemon":"Woobat","encounterrate":0.1},{"pokemon":"Numel","encounterrate":0.1}],"night":[{"pokemon":"Geodude-alola","encounterrate":0.2},{"pokemon":"Noibat","encounterrate":0.1},{"pokemon":"Rolycoly","encounterrate":0.1}]}},{"route":"Route 4","encounter_info":{"always":[{"pokemon":"Pachirisu","encounterrate":0.1},{"pokemon":"Flabebe","encounterrate":0.05},{"pokemon":"Buneary","encounterrate":0.1},{"pokemon":"Yanma","encounterrate":0.02},{"pokemon":"Pidove","encounterrate":0.2}],"day":[{"pokemon":"Pumpkaboo-M","encounterrate":0.08},{"pokemon":"Bellsprout","encounterrate":0.2},{"pokemon":"Pumpkaboo","encounterrate":0.05},{"pokemon":"Shinx","encounterrate":0.1},{"pokemon":"Glameow","encounterrate":0.1}],"night":[{"pokemon":"Stunky","encounterrate":0.1},{"pokemon":"Phantump","encounterrate":0.05},{"pokemon":"Oddish","encounterrate":0.2},{"pokemon":"Pumpkaboo-L","encounterrate":0.08},{"pokemon":"Mareep","encounterrate":0.1}]}},{"route":"Route 24","encounter_info":{"always":[{"pokemon":"Whismur","encounterrate":0.1},{"pokemon":"Ralts","encounterrate":0.08},{"pokemon":"Karrablast","encounterrate":0.1},{"pokemon":"Abra","encounterrate":0.1},{"pokemon":"Snubbull","encounterrate":0.2},{"pokemon":"Farfetch'd","encounterrate":0.05}],"day":[{"pokemon":"Elekid","encounterrate":0.05},{"pokemon":"Volbeat","encounterrate":0.1},{"pokemon":"Petilil","encounterrate":0.2},{"pokemon":"Ponyta","encounterrate":0.02}],"night":[{"pokemon":"Ponyta-galar","encounterrate":0.02},{"pokemon":"Cottonee","encounterrate":0.2},{"pokemon":"Illumise","encounterrate":0.1},{"pokemon":"Magby","encounterrate":0.05}]}},{"route":"Route 25","encounter_info":{"always":[{"pokemon":"Swablu","encounterrate":0.2},{"pokemon":"Taillow","encounterrate":0.2},{"pokemon":"Audino","encounterrate":0.05}],"day":[{"pokemon":"Yamper","encounterrate":0.05},{"pokemon":"Doduo","encounterrate":0.1},{"pokemon":"Zangoose","encounterrate":0.02},{"pokemon":"Pineco","encounterrate":0.1},{"pokemon":"Poliwag","encounterrate":0.1},{"pokemon":"Marill","encounterrate":0.1},{"pokemon":"Aipom","encounterrate":0.08}],"night":[{"pokemon":"Murkrow","encounterrate":0.1},{"pokemon":"Slakoth","encounterrate":0.08},{"pokemon":"Venonat","encounterrate":0.1},{"pokemon":"Psyduck","encounterrate":0.1},{"pokemon":"Buizel","encounterrate":0.1},{"pokemon":"Purrloin","encounterrate":0.05},{"pokemon":"Seviper","encounterrate":0.02}]}},{"route":"Route 5","encounter_info":{"always":[{"pokemon":"Growlithe","encounterrate":0.05},{"pokemon":"Drifloon","encounterrate":0.02},{"pokemon":"Morelull","encounterrate":0.1},{"pokemon":"Hatenna","encounterrate":0.2}],"day":[{"pokemon":"Vulpix","encounterrate":0.05},{"pokemon":"Solosis","encounterrate":0.2},{"pokemon":"Meowth","encounterrate":0.2},{"pokemon":"Swirlix","encounterrate":0.1},{"pokemon":"Grimer","encounterrate":0.08}],"night":[{"pokemon":"Gothita","encounterrate":0.2},{"pokemon":"Grimer-alola","encounterrate":0.08},{"pokemon":"Vulpix-alola","encounterrate":0.1},{"pokemon":"Meowth-galar","encounterrate":0.2},{"pokemon":"Spritzee","encounterrate":0.1}]}},{"route":"Route 6","encounter_info":{"always":[{"pokemon":"Sizzlipede","encounterrate":0.1},{"pokemon":"Dedenne","encounterrate":0.1},{"pokemon":"Togepi","encounterrate":0.02},{"pokemon":"Furfrou","encounterrate":0.1},{"pokemon":"Meditite","encounterrate":0.08}],"day":[{"pokemon":"Cherubi","encounterrate":0.2},{"pokemon":"Lickitung","encounterrate":0.1},{"pokemon":"Sunkern","encounterrate":0.2},{"pokemon":"Gulpin","encounterrate":0.1}],"night":[{"pokemon":"Komala","encounterrate":0.1},{"pokemon":"Bounsweet","encounterrate":0.2},{"pokemon":"Trubbish","encounterrate":0.1},{"pokemon":"Gossifleur","encounterrate":0.2}]}},{"route":"Route 11","encounter_info":{"always":[{"pokemon":"Ducklett","encounterrate":0.2},{"pokemon":"Bunnelby","encounterrate":0.1},{"pokemon":"Sigilyph","encounterrate":0.02},{"pokemon":"Drowzee","encounterrate":0.1},{"pokemon":"Scraggy","encounterrate":0.1},{"pokemon":"Baltoy","encounterrate":0.1}],"day":[{"pokemon":"Maractus","encounterrate":0.1},{"pokemon":"Stufful","encounterrate":0.2},{"pokemon":"Sandyghast","encounterrate":0.08}],"night":[{"pokemon":"Pancham","encounterrate":0.2},{"pokemon":"Golett","encounterrate":0.08},{"pokemon":"Cacnea","encounterrate":0.1}]}},{"route":"Diglett's Cave 2","encounter_info":{"always":[{"pokemon":"Sandile","encounterrate":0.1},{"pokemon":"Hippopotas","encounterrate":0.02},{"pokemon":"Gligar","encounterrate":0.05}],"day":[{"pokemon":"Diglett","encounterrate":0.4},{"pokemon":"Silicobra","encounterrate":0.1},{"pokemon":"Wooper","encounterrate":0.1},{"pokemon":"Drilbur","encounterrate":0.05},{"pokemon":"Dugtrio","encounterrate":0.08},{"pokemon":"Stunfisk","encounterrate":0.1}],"night":[{"pokemon":"Stunfisk-galar","encounterrate":0.1},{"pokemon":"Shellos","encounterrate":0.1},{"pokemon":"Diglett-alola","encounterrate":0.4},{"pokemon":"Phanpy","encounterrate":0.2},{"pokemon":"Dugtrio-alola","encounterrate":0.08}]}},{"route":"Route 9","encounter_info":{"always":[{"pokemon":"Corvisquire","encounterrate":0.1},{"pokemon":"Shelmet ","encounterrate":0.2},{"pokemon":"Dewpider","encounterrate":0.1},{"pokemon":"Tropius","encounterrate":0.08},{"pokemon":"Skorupi","encounterrate":0.02}],"day":[{"pokemon":"Mime Jr.","encounterrate":0.1},{"pokemon":"Indeedee","encounterrate":0.1},{"pokemon":"Exeggcute","encounterrate":0.2},{"pokemon":"Darumaka","encounterrate":0.1}],"night":[{"pokemon":"Indeedee-F","encounterrate":0.1},{"pokemon":"Exeggcute-alola","encounterrate":0.2},{"pokemon":"Salandit","encounterrate":0.1},{"pokemon":"Espurr","encounterrate":0.1}]}},{"route":"Route 10","encounter_info":{"always":[{"pokemon":"Croagunk","encounterrate":0.02},{"pokemon":"Magnemite","encounterrate":0.08},{"pokemon":"Pincurchin","encounterrate":0.1},{"pokemon":"Voltorb","encounterrate":0.2},{"pokemon":"Skitty","encounterrate":0.1},{"pokemon":"Emolga","encounterrate":0.1}],"day":[{"pokemon":"Plusle","encounterrate":0.1},{"pokemon":"Helioptile","encounterrate":0.4}],"night":[{"pokemon":"Minun","encounterrate":0.1},{"pokemon":"Electrike","encounterrate":0.4}]}},{"route":"Rock Tunnel","encounter_info":{"always":[{"pokemon":"Ferroseed","encounterrate":0.05},{"pokemon":"Durant","encounterrate":0.02},{"pokemon":"Minior","encounterrate":0.05},{"pokemon":"Aron","encounterrate":0.2},{"pokemon":"Zubat","encounterrate":0.1},{"pokemon":"Stonjourner","encounterrate":0.04},{"pokemon":"Heatmor","encounterrate":0.04},{"pokemon":"Carbink","encounterrate":0.1}],"day":[{"pokemon":"Solrock","encounterrate":0.1},{"pokemon":"Shuckle","encounterrate":0.1},{"pokemon":"Graveler","encounterrate":0.2}],"night":[{"pokemon":"Graveler-alola","encounterrate":0.2},{"pokemon":"Lunatone","encounterrate":0.1},{"pokemon":"Dwebble","encounterrate":0.1}]}},{"route":"Rock Tunnel B1F","encounter_info":{"always":[{"pokemon":"Bonsly","encounterrate":0.1},{"pokemon":"Swinub","encounterrate":0.1},{"pokemon":"Klink","encounterrate":0.02}],"day":[{"pokemon":"Snorunt","encounterrate":0.1},{"pokemon":"Sandslash","encounterrate":0.2},{"pokemon":"Boldore","encounterrate":0.2},{"pokemon":"Bronzor","encounterrate":0.1},{"pokemon":"Cubchoo","encounterrate":0.08},{"pokemon":"Carkol","encounterrate":0.1}],"night":[{"pokemon":"Rhyhorn","encounterrate":0.2},{"pokemon":"Nosepass","encounterrate":0.1},{"pokemon":"Onix","encounterrate":0.1},{"pokemon":"Sneasel","encounterrate":0.08},{"pokemon":"Sandslash-alola","encounterrate":0.2},{"pokemon":"Cubone","encounterrate":0.1}]}},{"route":"Route 7","encounter_info":{"always":[{"pokemon":"Cutiefly","encounterrate":0.1},{"pokemon":"Mienfoo","encounterrate":0.08},{"pokemon":"Porygon","encounterrate":0.02},{"pokemon":"Applin","encounterrate":0.1},{"pokemon":"Inkay","encounterrate":0.2}],"day":[{"pokemon":"Passimian","encounterrate":0.1},{"pokemon":"Rufflet","encounterrate":0.2},{"pokemon":"Deerling","encounterrate":0.2}],"night":[{"pokemon":"Deerling-Winter","encounterrate":0.2},{"pokemon":"Oranguru","encounterrate":0.1},{"pokemon":"Vullaby","encounterrate":0.2}]}},{"route":"Route 8","encounter_info":{"always":[{"pokemon":"Minccino","encounterrate":0.2},{"pokemon":"Comfey","encounterrate":0.1},{"pokemon":"Miltank","encounterrate":0.02},{"pokemon":"Kirlia","encounterrate":0.1},{"pokemon":"Lombre","encounterrate":0.2},{"pokemon":"Venipede","encounterrate":0.2}],"day":[{"pokemon":"Stantler","encounterrate":0.08},{"pokemon":"Vulpix","encounterrate":0.1}],"night":[{"pokemon":"Growlithe","encounterrate":0.1},{"pokemon":"Girafarig","encounterrate":0.08}]}},{"route":"Pokémon Tower","encounter_info":{"always":[{"pokemon":"Polteageist","encounterrate":0.08},{"pokemon":"Spiritomb","encounterrate":0.05},{"pokemon":"Mismagius","encounterrate":0.2},{"pokemon":"Sableye","encounterrate":0.05},{"pokemon":"Haunter","encounterrate":0.2},{"pokemon":"Lampent","encounterrate":0.02},{"pokemon":"Dusclops","encounterrate":0.1},{"pokemon":"Cubone-alola","encounterrate":0.1}],"day":[{"pokemon":"Cofagrigus","encounterrate":0.2}],"night":[{"pokemon":"Runerigus ","encounterrate":0.2}]}},{"route":"Route 16","encounter_info":{"always":[{"pokemon":"Dodrio","encounterrate":0.1},{"pokemon":"Mudbray","encounterrate":0.2},{"pokemon":"Togedemaru","encounterrate":0.2},{"pokemon":"Audino","encounterrate":0.05},{"pokemon":"Hawlucha","encounterrate":0.02},{"pokemon":"Elgyem","encounterrate":0.08},{"pokemon":"Falinks","encounterrate":0.1}],"day":[{"pokemon":"Duosion","encounterrate":0.2},{"pokemon":"Gulpin","encounterrate":0.1}],"night":[{"pokemon":"Trubbish","encounterrate":0.1},{"pokemon":"Gothorita","encounterrate":0.2}]}},{"route":"Route 17","encounter_info":{"always":[{"pokemon":"Zebstrika","encounterrate":0.2},{"pokemon":"Hypno","encounterrate":0.1},{"pokemon":"Audino","encounterrate":0.1},{"pokemon":"Torkoal","encounterrate":0.1},{"pokemon":"Grumpig","encounterrate":0.1},{"pokemon":"Skarmory","encounterrate":0.02}],"day":[{"pokemon":"Muk","encounterrate":0.1},{"pokemon":"Weezing","encounterrate":0.2},{"pokemon":"Drampa","encounterrate":0.08}],"night":[{"pokemon":"Turtonator","encounterrate":0.08},{"pokemon":"Weezing-galar","encounterrate":0.2},{"pokemon":"Muk-alola","encounterrate":0.1}]}},{"route":"Route 18","encounter_info":{"always":[{"pokemon":"Altaria","encounterrate":0.1},{"pokemon":"Xatu","encounterrate":0.2},{"pokemon":"Leavanny","encounterrate":0.1},{"pokemon":"Eevee","encounterrate":0.02},{"pokemon":"Bisharp","encounterrate":0.08},{"pokemon":"Vigoroth","encounterrate":0.2},{"pokemon":"Abomasnow","encounterrate":0.1}],"day":[{"pokemon":"Toxicroak","encounterrate":0.1},{"pokemon":"Oricorio-Baile","encounterrate":0.1}],"night":[{"pokemon":"Drapion","encounterrate":0.1},{"pokemon":"Oricorio-Pom","encounterrate":0.1}]}},{"route":"Route 12","encounter_info":{"always":[{"pokemon":"Oricorio-Sensu","encounterrate":0.1},{"pokemon":"Bulbasaur","encounterrate":0.02},{"pokemon":"Camerupt","encounterrate":0.1},{"pokemon":"Pidgeot","encounterrate":0.2}],"day":[{"pokemon":"Munna","encounterrate":0.2},{"pokemon":"Swirlix","encounterrate":0.1},{"pokemon":"Pansear","encounterrate":0.1},{"pokemon":"Rapidash","encounterrate":0.1},{"pokemon":"Drifloon","encounterrate":0.08}],"night":[{"pokemon":"Musharna","encounterrate":0.2},{"pokemon":"Drifblim","encounterrate":0.08},{"pokemon":"Rapidash-galar","encounterrate":0.1},{"pokemon":"Spritzee","encounterrate":0.1},{"pokemon":"Simisear","encounterrate":0.1}]}},{"route":"Route 13","encounter_info":{"always":[{"pokemon":"Vanilluxe","encounterrate":0.2},{"pokemon":"Miltank","encounterrate":0.1},{"pokemon":"Oricorio-P'au","encounterrate":0.1},{"pokemon":"Charmander","encounterrate":0.02},{"pokemon":"Simisage","encounterrate":0.1},{"pokemon":"Lurantis","encounterrate":0.1},{"pokemon":"Tangrowth","encounterrate":0.2}],"day":[{"pokemon":"Zangoose","encounterrate":0.08},{"pokemon":"Roselia","encounterrate":0.1}],"night":[{"pokemon":"Seviper","encounterrate":0.08},{"pokemon":"Nuzleaf","encounterrate":0.1}]}},{"route":"Route 14","encounter_info":{"always":[{"pokemon":"Pelipper","encounterrate":0.2},{"pokemon":"Torkoal","encounterrate":0.2},{"pokemon":"Swadloon","encounterrate":0.2},{"pokemon":"Durant","encounterrate":0.08},{"pokemon":"Charjabug","encounterrate":0.1},{"pokemon":"Golisopod","encounterrate":0.02}],"day":[{"pokemon":"Whirlipede","encounterrate":0.2}],"night":[{"pokemon":"Palossand","encounterrate":0.2}]}},{"route":"Route 15","encounter_info":{"always":[{"pokemon":"Ambipom","encounterrate":0.2},{"pokemon":"Amoonguss","encounterrate":0.2},{"pokemon":"Galvantula","encounterrate":0.1},{"pokemon":"Oricorio-Baile","encounterrate":0.1},{"pokemon":"Ferrothorn","encounterrate":0.08},{"pokemon":"Tsareena","encounterrate":0.1},{"pokemon":"Ditto","encounterrate":0.02},{"pokemon":"Sigilyph","encounterrate":0.1}],"day":[{"pokemon":"Panpour","encounterrate":0.1}],"night":[{"pokemon":"Simipour","encounterrate":0.1}]}},{"route":"Safari Zone 1","encounter_info":{"always":[{"pokemon":"Absol","encounterrate":0.2},{"pokemon":"Chansey","encounterrate":0.02},{"pokemon":"Kecleon","encounterrate":0.2},{"pokemon":"Meltan","encounterrate":0.2},{"pokemon":"Spinda","encounterrate":0.2},{"pokemon":"Porygon","encounterrate":0.1}],"day":[{"pokemon":"Scyther","encounterrate":0.08}],"night":[{"pokemon":"Heracross","encounterrate":0.08}]}},{"route":"Safari Zone 2","encounter_info":{"always":[{"pokemon":"Castform","encounterrate":0.2},{"pokemon":"Wobbuffet","encounterrate":0.2},{"pokemon":"Kangaskhan","encounterrate":0.02},{"pokemon":"Zorua","encounterrate":0.1},{"pokemon":"Pinsir","encounterrate":0.08},{"pokemon":"Hawlucha","encounterrate":0.2}],"day":[{"pokemon":"Bouffalant","encounterrate":0.2}],"night":[{"pokemon":"Tauros","encounterrate":0.2}]}},{"route":"Safari Zone 3","encounter_info":{"always":[{"pokemon":"Binacle","encounterrate":0.08},{"pokemon":"Axew","encounterrate":0.02},{"pokemon":"Klefki","encounterrate":0.4},{"pokemon":"Bisharp","encounterrate":0.2},{"pokemon":"Skarmory","encounterrate":0.1}],"day":[{"pokemon":"Sawk","encounterrate":0.2}],"night":[{"pokemon":"Throh","encounterrate":0.2}]}},{"route":"Safari Zone 4","encounter_info":{"always":[{"pokemon":"Hippowdon","encounterrate":0.2},{"pokemon":"Crabominable","encounterrate":0.08},{"pokemon":"Yanma","encounterrate":0.1},{"pokemon":"Smeargle","encounterrate":0.02},{"pokemon":"Vespiquen","encounterrate":0.2},{"pokemon":"Druddigon","encounterrate":0.4}],"day":[],"night":[]}},{"route":"Route 21","encounter_info":{"always":[{"pokemon":"Ariados","encounterrate":0.08},{"pokemon":"Victreebel","encounterrate":0.02},{"pokemon":"Nidorino","encounterrate":0.2},{"pokemon":"Kricketune","encounterrate":0.1},{"pokemon":"Kingler","encounterrate":0.4},{"pokemon":"Weepinbell","encounterrate":0.2}],"day":[],"night":[]}},{"route":"Seafoam Islands B1F","encounter_info":{"always":[{"pokemon":"Golbat","encounterrate":0.1},{"pokemon":"Avalugg","encounterrate":0.08},{"pokemon":"Snorunt","encounterrate":0.2},{"pokemon":"Jynx","encounterrate":0.02},{"pokemon":"Beartic","encounterrate":0.2}],"day":[{"pokemon":"Piloswine","encounterrate":0.2},{"pokemon":"Slowbro","encounterrate":0.2}],"night":[{"pokemon":"Walrein","encounterrate":0.2},{"pokemon":"Sandslash-alola","encounterrate":0.2}]}},{"route":"Seafoam islands B2F","encounter_info":{"always":[{"pokemon":"Golbat","encounterrate":0.1},{"pokemon":"Vanilluxe","encounterrate":0.2},{"pokemon":"Delibird","encounterrate":0.02},{"pokemon":"Cryogonal","encounterrate":0.08},{"pokemon":"Darmanitan-galar","encounterrate":0.2}],"day":[{"pokemon":"Piloswine","encounterrate":0.2},{"pokemon":"Slowking","encounterrate":0.2}],"night":[{"pokemon":"Sandslash-alola","encounterrate":0.2},{"pokemon":"Golduck","encounterrate":0.2}]}},{"route":"Seafoam Islands B3F","encounter_info":{"always":[{"pokemon":"Sneasel","encounterrate":0.08},{"pokemon":"Ninetales-alola","encounterrate":0.2},{"pokemon":"Golbat","encounterrate":0.1},{"pokemon":"Delibird","encounterrate":0.02},{"pokemon":"Abomasnow","encounterrate":0.2}],"day":[{"pokemon":"Snover","encounterrate":0.2},{"pokemon":"Crawdaunt","encounterrate":0.2}],"night":[{"pokemon":"Snorunt","encounterrate":0.2},{"pokemon":"Kingler","encounterrate":0.2}]}},{"route":"Seafoam Islands B4F","encounter_info":{"always":[{"pokemon":"Darmanitan-galar","encounterrate":0.2},{"pokemon":"Frosmoth","encounterrate":0.08},{"pokemon":"Jynx","encounterrate":0.02},{"pokemon":"Ninetales-alola","encounterrate":0.2},{"pokemon":"Golbat","encounterrate":0.1}],"day":[{"pokemon":"Piloswine","encounterrate":0.2},{"pokemon":"Dewgong","encounterrate":0.2}],"night":[{"pokemon":"Golduck","encounterrate":0.2},{"pokemon":"Sandslash-alola","encounterrate":0.2}]}},{"route":"Pkmn Mansion 1F","encounter_info":{"always":[{"pokemon":"Audino","encounterrate":0.2},{"pokemon":"Liepard","encounterrate":0.1},{"pokemon":"Chimecho","encounterrate":0.02},{"pokemon":"Sableye","encounterrate":0.08}],"day":[{"pokemon":"Muk","encounterrate":0.2},{"pokemon":"Raticate","encounterrate":0.2},{"pokemon":"Weezing","encounterrate":0.1},{"pokemon":"Arcanine","encounterrate":0.1}],"night":[{"pokemon":"Raticate-alola","encounterrate":0.2},{"pokemon":"Ninetales","encounterrate":0.1},{"pokemon":"Muk-alola","encounterrate":0.2},{"pokemon":"Weezing-galar","encounterrate":0.1}]}},{"route":"Pkmn Mansion 2F","encounter_info":{"always":[{"pokemon":"Mightyena","encounterrate":0.1},{"pokemon":"Koffing","encounterrate":0.1},{"pokemon":"Heatmor","encounterrate":0.1},{"pokemon":"Banette","encounterrate":0.08},{"pokemon":"Swalot","encounterrate":0.1},{"pokemon":"Garbodor","encounterrate":0.2},{"pokemon":"Chimecho","encounterrate":0.02}],"day":[{"pokemon":"Houndoom","encounterrate":0.1},{"pokemon":"Gumshoos","encounterrate":0.2}],"night":[{"pokemon":"Obstagoon","encounterrate":0.2},{"pokemon":"Salazzle","encounterrate":0.1}]}},{"route":"Pkmn Mansion 3F","encounter_info":{"always":[{"pokemon":"Skuntank","encounterrate":0.1},{"pokemon":"Chimecho","encounterrate":0.02},{"pokemon":"Seviper","encounterrate":0.2},{"pokemon":"Chandelure","encounterrate":0.1},{"pokemon":"Krookodile","encounterrate":0.08},{"pokemon":"Ariados","encounterrate":0.2}],"day":[{"pokemon":"Bewear","encounterrate":0.2},{"pokemon":"Rapidash","encounterrate":0.1}],"night":[{"pokemon":"Komala","encounterrate":0.2},{"pokemon":"Rapidash-galar","encounterrate":0.1}]}},{"route":"Pkmn Mansion B1F","encounter_info":{"always":[{"pokemon":"Chimecho","encounterrate":0.02},{"pokemon":"Mightyena","encounterrate":0.1},{"pokemon":"Garbodor","encounterrate":0.2},{"pokemon":"Ariados","encounterrate":0.2},{"pokemon":"Magmar","encounterrate":0.1},{"pokemon":"Banette","encounterrate":0.08}],"day":[{"pokemon":"Arcanine","encounterrate":0.1},{"pokemon":"Raticate","encounterrate":0.2}],"night":[{"pokemon":"Ninetales","encounterrate":0.1},{"pokemon":"Raticate-alola","encounterrate":0.2}]}},{"route":"Power Plant","encounter_info":{"always":[{"pokemon":"Magneton","encounterrate":0.2},{"pokemon":"Electabuzz","encounterrate":0.32},{"pokemon":"Electrode","encounterrate":0.2},{"pokemon":"Ampharos","encounterrate":0.2}],"day":[{"pokemon":"Dedenne","encounterrate":0.1},{"pokemon":"Zebstrika","encounterrate":0.1},{"pokemon":"Eelektross","encounterrate":0.1}],"night":[{"pokemon":"Togedemaru","encounterrate":0.1},{"pokemon":"Vikavolt","encounterrate":0.1},{"pokemon":"Manectric","encounterrate":0.1}]}},{"route":"Cerulean Cave","encounter_info":{"always":[{"pokemon":"Duraludon","encounterrate":0.08},{"pokemon":"Type:Null","encounterrate":0.02},{"pokemon":"Parasect","encounterrate":0.2},{"pokemon":"Seismitoad","encounterrate":0.1},{"pokemon":"Golbat","encounterrate":0.2},{"pokemon":"Magneton","encounterrate":0.2}],"day":[{"pokemon":"Machamp","encounterrate":0.2}],"night":[{"pokemon":"Conkeldurr","encounterrate":0.2}]}},{"route":"Cerulean Cave 2F","encounter_info":{"always":[{"pokemon":"Type:Null","encounterrate":0.02},{"pokemon":"Duraludon","encounterrate":0.08},{"pokemon":"Audino","encounterrate":0.2},{"pokemon":"Swoobat","encounterrate":0.2},{"pokemon":"Amoonguss","encounterrate":0.2}],"day":[{"pokemon":"Alakazam","encounterrate":0.1},{"pokemon":"Primeape","encounterrate":0.2}],"night":[{"pokemon":"Reuniclus","encounterrate":0.1},{"pokemon":"Pangoro","encounterrate":0.2}]}},{"route":"Cerulean Cave B1F","encounter_info":{"always":[{"pokemon":"Lopunny","encounterrate":0.2},{"pokemon":"Excadrill","encounterrate":0.08},{"pokemon":"Type:Null","encounterrate":0.02},{"pokemon":"Noivern","encounterrate":0.2},{"pokemon":"Gardevoir","encounterrate":0.2},{"pokemon":"Shiinotic","encounterrate":0.2}],"day":[{"pokemon":"Medicham","encounterrate":0.2}],"night":[{"pokemon":"Toxicroak","encounterrate":0.2}]}},{"route":"Route 23","encounter_info":{"always":[{"pokemon":"Simipour","encounterrate":0.2},{"pokemon":"Staraptor","encounterrate":0.02},{"pokemon":"Simisage","encounterrate":0.1},{"pokemon":"Fearow","encounterrate":0.2},{"pokemon":"Seviper","encounterrate":0.1},{"pokemon":"Golbat","encounterrate":0.08},{"pokemon":"Primeape","encounterrate":0.2},{"pokemon":"Simisear","encounterrate":0.1}],"day":[],"night":[]}},{"route":"Victory Road 1F","encounter_info":{"always":[{"pokemon":"Audino","encounterrate":0.2},{"pokemon":"Arbok","encounterrate":0.08},{"pokemon":"Marowak","encounterrate":0.02},{"pokemon":"Steelix","encounterrate":0.2},{"pokemon":"Golem","encounterrate":0.2},{"pokemon":"Golbat","encounterrate":0.1},{"pokemon":"Machamp","encounterrate":0.2}],"day":[],"night":[]}},{"route":"Victory Road 2F","encounter_info":{"always":[{"pokemon":"Golem","encounterrate":0.2},{"pokemon":"Primeape","encounterrate":0.2},{"pokemon":"Machamp","encounterrate":0.02},{"pokemon":"Arbok","encounterrate":0.1},{"pokemon":"Marowak","encounterrate":0.08},{"pokemon":"Golbat","encounterrate":0.2},{"pokemon":"Audino","encounterrate":0.2}],"day":[],"night":[]}},{"route":"Victory Road 3F","encounter_info":{"always":[{"pokemon":"Arbok","encounterrate":0.4},{"pokemon":"Audino","encounterrate":0.2},{"pokemon":"Marowak","encounterrate":0.08},{"pokemon":"Machamp","encounterrate":0.02},{"pokemon":"Palossand","encounterrate":0.2},{"pokemon":"Golbat","encounterrate":0.4}],"day":[],"night":[]}}]}]}